{
  "miniprogramRoot": "dist/",
  "projectname": "Suiyue-App",
  "description": "Tang and Song Poetry Analysis App",
  "appid": "touristappid",
  "setting": {
    "urlCheck": false,
    "es6": true,
    "enhance": true,
    "postcss": true,
    "preloadBackgroundData": false,
    "minified": true,
    "newFeature": true,
    "coverView": true,
    "nodeModules": true,
    "autoAudits": false,
    "showShadowRootInWxmlPanel": true,
    "scopeDataCheck": false,
    "uglifyFileName": false,
    "checkInvalidSitemap": true
  },
  "compileType": "miniprogram",
  "libVersion": "2.19.4",
  "packOptions": {
    "ignore": [],
    "include": []
  },
  "editorSetting": {
    "tabIndent": "insertSpaces",
    "tabSize": 2
  }
}